chat_with_sql/__init__.py
chat_with_sql/chat_with_sql.py
tests/__init__.py
tests/test_chat_with_sql.py
chatwithsql-0.1.3.dist-info/LICENSE
chatwithsql-0.1.3.dist-info/METADATA
chatwithsql-0.1.3.dist-info/WHEEL
chatwithsql-0.1.3.dist-info/top_level.txt
chatwithsql-0.1.3.dist-info/RECORD
