Metadata-Version: 2.1
Name: chatwithsql
Version: 0.1.3
Summary: ChatWithSQL: Secure, Schema-Validated Text-to-SQL, Eliminating Arbitrary Query Risks from LLMs
Home-page: https://github.com/sathninduk/ChatWithSQL
Author: Sathnindu Kottage
Author-email: hello@bysatha.com
Classifier: Programming Language :: Python :: 3
Classifier: License :: OSI Approved :: MIT License
Classifier: Operating System :: OS Independent
Requires-Python: >=3.6
License-File: LICENSE
Requires-Dist: llama-index
Requires-Dist: llama-index-readers-database
Requires-Dist: llama-index-llms-openai
Requires-Dist: llama-index-llms-gemini
Requires-Dist: llama-index-llms-llama-api
Requires-Dist: llama-index-llms-ollama
Requires-Dist: python-dotenv
Requires-Dist: psycopg2
